<annotation>
	<folder>collectedimages</folder>
	<filename>thanks.7016a4fa-c4cc-11ec-ad98-acde48001122.jpg</filename>
	<path>/Users/nathanyoon/RealTimeObjectDetection/Tensorflow/workspace/images/collectedimages/thanks.7016a4fa-c4cc-11ec-ad98-acde48001122.jpg</path>
	<source>
		<database>Unknown</database>
	</source>
	<size>
		<width>1280</width>
		<height>720</height>
		<depth>3</depth>
	</size>
	<segmented>0</segmented>
	<object>
		<name>Thank You</name>
		<pose>Unspecified</pose>
		<truncated>0</truncated>
		<difficult>0</difficult>
		<bndbox>
			<xmin>303</xmin>
			<ymin>361</ymin>
			<xmax>1018</xmax>
			<ymax>510</ymax>
		</bndbox>
	</object>
</annotation>
